bentoml_comfyui-0.1.2.dist-info/METADATA
bentoml_comfyui-0.1.2.dist-info/WHEEL
bentoml_comfyui-0.1.2.dist-info/entry_points.txt
bentoml_comfyui-0.1.2.dist-info/licenses/LICENSE
bentoml_comfyui/__init__.py
bentoml_comfyui/_core.py
bentoml_comfyui/_service.tpl
bentoml_comfyui/cli.py
bentoml_comfyui/py.typed
bentoml_comfyui-0.1.2.dist-info/RECORD
